[
    {
        "a": [
            "\u014drn\u0101menta"
        ],
        "q": "Gemmae et margar\u012btae # pulchra sunt."
    },
    {
        "a": [
            "accipit"
        ],
        "q": "Aemilia multa \u014drn\u0101menta \u0101 I\u016bli\u014d #."
    },
    {
        "a": [
            "margar\u012bt\u0101s",
            "digit\u014d"
        ],
        "q": "Aemilia # in coll\u014d et \u0101nulum in # habet."
    },
    {
        "a": [
            "c\u014dnsistunt"
        ],
        "q": "Multae f\u0113minae ante tabernam Alb\u012bn\u012b # et \u014drn\u0101menta eius aspiciunt."
    },
    {
        "a": [
            "emunt"
        ],
        "q": "Vir\u012b \u014drn\u0101menta # et f\u0113min\u012bs dant."
    },
    {
        "a": [
            "\u0100nulus",
            "c\u014dnstat"
        ],
        "q": "# gemm\u0101tus centum s\u0113sterti\u012bs #."
    },
    {
        "a": [
            "Pretium",
            "n\u014dn\u0101gint\u0101"
        ],
        "q": "# \u0101nul\u012b est centum s\u0113sterti\u012b, sed M\u0113dus # [XC] tantum habet."
    },
    {
        "a": [
            "satis"
        ],
        "q": "Alb\u012bnus: \"N\u014dn\u0101gint\u0101 n\u014dn # est!\""
    },
    {
        "a": [
            "aut"
        ],
        "q": "M\u0113dus: \"Accipe n\u014dn\u0101gint\u0101 s\u0113sterti\u014ds # n\u016bll\u014ds!\""
    },
    {
        "a": [
            "convenit",
            "nimis"
        ],
        "q": "\u0100nulus ad digitum medium n\u014dn # : digitus medius # magnus est."
    },
    {
        "a": [
            "qu\u0101rtum",
            "tantus",
            "medius"
        ],
        "q": "Sed \u0101nulus convenit ad digitum # [IV], qu\u012b n\u014dn # est quantus digitus #."
    },
    {
        "a": [
            "aspicit",
            "abit"
        ],
        "q": "L\u0233dia laeta digitum suum # et cum M\u0113d\u014d \u0101 tabern\u0101 #."
    },
    {
        "a": [
            "m\u014dnstrat"
        ],
        "q": "L\u0233dia M\u0113d\u014d viam #."
    }
]