[
    {
        "a": [
            "v\u012bll\u0101",
            "habitat",
            "e\u014d"
        ],
        "q": "I\u016blius in magn\u0101 # #. Aemilia cum # [: I\u016bli\u014d] habitat."
    },
    {
        "a": [
            "amat",
            "ea",
            "pulchra"
        ],
        "q": "I\u016blius Aemiliam #, quia # [: Aemilia] bona et # f\u0113mina est."
    },
    {
        "a": [
            "cum",
            "sine"
        ],
        "q": "Aemilia in perist\u0233l\u014d est # l\u012bber\u012bs su\u012bs, sed # vir\u014d su\u014d."
    },
    {
        "a": [
            "ab",
            "hort\u014d"
        ],
        "q": "I\u016blia # Aemili\u0101 disc\u0113dit; iam puella in # est."
    },
    {
        "a": [
            "carpit",
            "ex",
            "ros\u012bs"
        ],
        "q": "I\u016blia ros\u0101s # et # hort\u014d venit cum V #."
    },
    {
        "a": [
            "d\u0113lectant"
        ],
        "q": "Puella laeta est: rosae eam #."
    },
    {
        "a": [
            "Id",
            "\u0101tri\u014d"
        ],
        "q": "Ubi est impluvium? # [: impluvium] est in #."
    },
    {
        "a": [
            "aqua",
            "fenestrae"
        ],
        "q": "In impluvi\u014d # est. In \u0101tri\u014d n\u016bllae # sunt."
    }
]