[
    {
        "a": [
            "is",
            "a"
        ],
        "q": "Membra corpor# h\u016bm\u0101n\u012b sunt duo bracchia et duo cr\u016br#."
    },
    {
        "a": [
            "e",
            "um",
            "a"
        ],
        "q": "In corpor# h\u016bm\u0101n\u014d \u016bn# caput est, n\u014dn duo capit#."
    },
    {
        "a": [
            "e",
            "\u0113s",
            "um"
        ],
        "q": "In capit# sunt duae aur# et \u016bn# \u014ds."
    },
    {
        "a": [
            "e",
            "\u0113s"
        ],
        "q": "In \u014dr# sunt dent#."
    },
    {
        "a": [
            "e",
            "um",
            "\u0113s"
        ],
        "q": "In pector# \u016bn# cor et duo pulm\u014dn# sunt."
    },
    {
        "a": [
            "um",
            "\u0113re",
            "um",
            "\u012bre"
        ],
        "q": "Medicus Qu\u012bnt# super lectum iac# videt; medicus puer# dorm# videt."
    },
    {
        "a": [
            "us",
            "it",
            "um",
            "\u012bre"
        ],
        "q": "Medicus: \"Qu\u012bnt# dorm#.\" Medicus 'Qu\u012bnt# dorm# ' d\u012bcit."
    },
    {
        "a": [
            "um",
            "ere",
            "am",
            "am",
            "se"
        ],
        "q": "Medicus puer# linguam ostend# iubet, et 'lingu# eius rubr# es# ' d\u012bcit."
    },
    {
        "a": [
            "em",
            "\u0113re"
        ],
        "q": "Puer d\u012bcit 'ped# et caput dol#.'"
    },
    {
        "a": [
            "am",
            "\u0113re"
        ],
        "q": "Medicus Aemili# p\u014dculum ten# iubet."
    },
    {
        "a": [
            "um",
            "\u0101re",
            "it",
            "um",
            "um",
            "se"
        ],
        "q": "Syra Qu\u012bnt# sp\u012br# n\u014dn aud#, itaque Syra e# mortu# es# putat."
    },
    {
        "a": [
            "us",
            "it"
        ],
        "q": "Sed Qu\u012bnt# v\u012bv#."
    },
    {
        "a": [
            "um",
            "ere"
        ],
        "q": "M\u0101ter f\u012bli# v\u012bv# gaudet."
    },
    {
        "a": [
            "um",
            "um",
            "\u012bre"
        ],
        "q": "Necesse est puer# aegr# dorm#."
    }
]